xtructure/__init__.py
xtructure/numpy.py
xtructure/xtructure_numpy.py
xtructure/bgpq/__init__.py
xtructure/bgpq/bgpq.py
xtructure/bgpq/merge_split/__init__.py
xtructure/bgpq/merge_split/common.py
xtructure/bgpq/merge_split/loop.py
xtructure/bgpq/merge_split/parallel.py
xtructure/bgpq/merge_split/split.py
xtructure/core/__init__.py
xtructure/core/dataclass.py
xtructure/core/field_descriptors.py
xtructure/core/protocol.py
xtructure/core/structuredtype.py
xtructure/core/xtructure_decorators/__init__.py
xtructure/core/xtructure_decorators/annotate.py
xtructure/core/xtructure_decorators/default.py
xtructure/core/xtructure_decorators/hash.py
xtructure/core/xtructure_decorators/indexing.py
xtructure/core/xtructure_decorators/io.py
xtructure/core/xtructure_decorators/ops.py
xtructure/core/xtructure_decorators/shape.py
xtructure/core/xtructure_decorators/string_format.py
xtructure/core/xtructure_decorators/structure_util.py
xtructure/core/xtructure_numpy/__init__.py
xtructure/core/xtructure_numpy/array_ops.py
xtructure/core/xtructure_numpy/dataclass_ops.py
xtructure/hashtable/__init__.py
xtructure/hashtable/hashtable.py
xtructure/io/__init__.py
xtructure/io/io.py
xtructure/queue/__init__.py
xtructure/queue/queue.py
xtructure/stack/__init__.py
xtructure/stack/stack.py
xtructure-0.1.1.dist-info/licenses/LICENSE
xtructure_benchmarks/__init__.py
xtructure_benchmarks/benchmark_hashtable.py
xtructure_benchmarks/benchmark_heap.py
xtructure_benchmarks/benchmark_queue.py
xtructure_benchmarks/benchmark_stack.py
xtructure_benchmarks/common.py
xtructure_benchmarks/run_all.py
xtructure_benchmarks/visualize.py
xtructure-0.1.1.dist-info/METADATA
xtructure-0.1.1.dist-info/WHEEL
xtructure-0.1.1.dist-info/top_level.txt
xtructure-0.1.1.dist-info/RECORD
