Metadata-Version: 2.4
Name: xtructure
Version: 0.1.1
Summary: JAX-optimized data structures
Home-page: https://github.com/tinker495/Xtructure
Author: tinker495
Author-email: wjdrbtjr495@gmail.com
Classifier: Programming Language :: Python :: 3
Classifier: License :: OSI Approved :: MIT License
Classifier: Operating System :: OS Independent
Classifier: Topic :: Scientific/Engineering :: Artificial Intelligence
Requires-Python: >=3.8
License-File: LICENSE
Requires-Dist: jax[cuda]<0.8.0,>=0.4.0
Requires-Dist: chex>=0.1.0
Requires-Dist: tabulate>=0.9.0
Requires-Dist: numpy>=2.2.0
Requires-Dist: rich
Provides-Extra: dev
Requires-Dist: pytest>=7.0.0; extra == "dev"
Dynamic: author
Dynamic: author-email
Dynamic: classifier
Dynamic: description
Dynamic: description-content-type
Dynamic: home-page
Dynamic: license-file
Dynamic: provides-extra
Dynamic: requires-dist
Dynamic: requires-python
Dynamic: summary
